lynkr/__init__.py
lynkr/client.py
lynkr/crypto.py
lynkr/exceptions.py
lynkr/public_key.pem
lynkr/schema.py
lynkr/keys/__init__.py
lynkr/keys/key_manager.py
lynkr/utils/__init__.py
lynkr/utils/http.py
lynkr/utils/validation.py
lynkr-0.1.11.dist-info/licenses/LICENSE
lynkr-0.1.11.dist-info/METADATA
lynkr-0.1.11.dist-info/WHEEL
lynkr-0.1.11.dist-info/top_level.txt
lynkr-0.1.11.dist-info/RECORD
