Metadata-Version: 2.4
Name: lynkr
Version: 0.1.11
Summary: Official Python SDK for Lynkr
Author-email: "Lynkr Inc." <info@lynkr.ca>
License: MIT
Project-URL: Homepage, https://github.com/Lynkr-Inc/lynkr-python-sdk
Project-URL: Bug Tracker, https://github.com/Lynkr-Inc/lynkr-python-sdk/issues
Project-URL: Documentation, https://docs.lynkr.ca/
Keywords: api,sdk,client
Classifier: Development Status :: 4 - Beta
Classifier: Intended Audience :: Developers
Classifier: License :: OSI Approved :: MIT License
Classifier: Programming Language :: Python :: 3
Classifier: Programming Language :: Python :: 3.8
Classifier: Programming Language :: Python :: 3.9
Classifier: Programming Language :: Python :: 3.10
Classifier: Programming Language :: Python :: 3.11
Classifier: Programming Language :: Python :: 3.12
Classifier: Topic :: Software Development :: Libraries :: Python Modules
Requires-Python: >=3.8
License-File: LICENSE
Requires-Dist: requests>=2.25.0
Requires-Dist: langchain
Requires-Dist: cryptography
Provides-Extra: dev
Requires-Dist: pytest>=7.0.0; extra == "dev"
Requires-Dist: pytest-cov>=4.0.0; extra == "dev"
Requires-Dist: black>=23.0.0; extra == "dev"
Requires-Dist: isort>=5.12.0; extra == "dev"
Requires-Dist: mypy>=1.0.0; extra == "dev"
Requires-Dist: flake8>=6.0.0; extra == "dev"
Requires-Dist: tox>=4.0.0; extra == "dev"
Provides-Extra: docs
Requires-Dist: mkdocs>=1.4.0; extra == "docs"
Requires-Dist: mkdocs-material>=9.0.0; extra == "docs"
Requires-Dist: mkdocstrings>=0.20.0; extra == "docs"
Requires-Dist: mkdocstrings-python>=1.0.0; extra == "docs"
Dynamic: license-file
